py4sync/__init__.py
py4sync/py4sync.py
py4sync-1.0.1.dist-info/METADATA
py4sync-1.0.1.dist-info/WHEEL
py4sync-1.0.1.dist-info/top_level.txt
py4sync-1.0.1.dist-info/RECORD
